timetable_announcer/__init__.py
timetable_announcer/announce.py
timetable_announcer-0.0.3.dist-info/LICENSE
timetable_announcer-0.0.3.dist-info/WHEEL
timetable_announcer-0.0.3.dist-info/METADATA
timetable_announcer-0.0.3.dist-info/RECORD
