Metadata-Version: 2.1
Name: timetable_announcer
Version: 0.0.3
Summary: Python timetable slot handler
Author-email: "John C. G. Sturdy" <jcg.sturdy@gmail.com>
Classifier: License :: OSI Approved :: GNU General Public License v3 or later (GPLv3+)
